ydiff.py
ydiff-1.5.dist-info/LICENSE
ydiff-1.5.dist-info/METADATA
ydiff-1.5.dist-info/WHEEL
ydiff-1.5.dist-info/entry_points.txt
ydiff-1.5.dist-info/top_level.txt
ydiff-1.5.dist-info/RECORD
