Metadata-Version: 2.1
Name: ydiff
Version: 1.5
Summary: View colored, incremental diff in a workspace or from stdin, in side-by-side or unified moded, and auto paged.
Home-page: https://github.com/ymattw/ydiff
Author: Matt Wang
License: BSD-3
Keywords: colored incremental side-by-side diff
Classifier: Development Status :: 5 - Production/Stable
Classifier: Topic :: Utilities
Classifier: License :: OSI Approved :: BSD License
Classifier: Environment :: Console
Classifier: Intended Audience :: Developers
Classifier: Operating System :: MacOS :: MacOS X
Classifier: Operating System :: POSIX
Classifier: Operating System :: Unix
Classifier: Programming Language :: Python
Classifier: Programming Language :: Python :: 3
Requires-Python: >=3.3
License-File: LICENSE
